{"totalHistoryAmount":4763,"TECNOLOGIA-occurances":2311,"TECNOLOGIA-percentage":48.51984043669956,"ESPORTE-occurances":679,"ESPORTE-percentage":14.255721184127651,"FACEBOOK-occurances":568,"FACEBOOK-percentage":11.925257190846105,"SEXO-occurances":412,"SEXO-percentage":8.650010497585555,"INSTAGRAM-occurances":67,"INSTAGRAM-percentage":1.406676464413185,"CARROS-occurances":62,"CARROS-percentage":1.3017006088599623,"YOUTUBE-occurances":46,"YOUTUBE-percentage":0.9657778710896494,"NOTÍCIAS-occurances":23,"NOTÍCIAS-percentage":0.4828889355448247,"CIÊNCIA-occurances":10,"CIÊNCIA-percentage":0.2099517111064455,"MODA-occurances":9,"MODA-percentage":0.18895653999580098,"DECORAÇÃO-occurances":8,"DECORAÇÃO-percentage":0.16796136888515642,"EDUCAÇÃO-occurances":6,"EDUCAÇÃO-percentage":0.1259710266638673,"ESOTERISMO-occurances":5,"ESOTERISMO-percentage":0.10497585555322275,"SÉRIES E FILMES-occurances":5,"SÉRIES E FILMES-percentage":0.10497585555322275,"POP/ARTE-occurances":2,"POP/ARTE-percentage":0.041990342221289105,"POLÍTICA-occurances":1,"POLÍTICA-percentage":0.020995171110644553,"TV E CELEBRIDADES-occurances":1,"TV E CELEBRIDADES-percentage":0.020995171110644553,"VIAGENS-occurances":1,"VIAGENS-percentage":0.020995171110644553,"ALIMENTAÇÃO E SAÚDE-occurances":0,"ALIMENTAÇÃO E SAÚDE-percentage":0,"ECONOMIA-occurances":0,"ECONOMIA-percentage":0,"FITNESS-occurances":0,"FITNESS-percentage":0,"HUMOR-occurances":0,"HUMOR-percentage":0,"INTERNACIONAL-occurances":0,"INTERNACIONAL-percentage":0,"JOGOS-occurances":0,"JOGOS-percentage":0,"LINKEDIN-occurances":0,"LINKEDIN-percentage":0,"NATUREZA-occurances":0,"NATUREZA-percentage":0,"TWITTER-occurances":0,"TWITTER-percentage":0}