{"totalHistoryAmount":7111,"TECNOLOGIA-occurances":3396,"TECNOLOGIA-percentage":47.756996203065675,"ESPORTE-occurances":1013,"ESPORTE-percentage":14.245535086485726,"FACEBOOK-occurances":956,"FACEBOOK-percentage":13.443960061875966,"SEXO-occurances":603,"SEXO-percentage":8.479819997187455,"INSTAGRAM-occurances":132,"INSTAGRAM-percentage":1.856279004359443,"CARROS-occurances":87,"CARROS-percentage":1.223456616509633,"YOUTUBE-occurances":59,"YOUTUBE-percentage":0.8297004640697511,"NOTÍCIAS-occurances":32,"NOTÍCIAS-percentage":0.450007031359865,"MODA-occurances":18,"MODA-percentage":0.25312895513992406,"ESOTERISMO-occurances":14,"ESOTERISMO-percentage":0.19687807621994094,"DECORAÇÃO-occurances":13,"DECORAÇÃO-percentage":0.18281535648994515,"LINKEDIN-occurances":11,"LINKEDIN-percentage":0.1546899170299536,"CIÊNCIA-occurances":10,"CIÊNCIA-percentage":0.14062719729995782,"SÉRIES E FILMES-occurances":7,"SÉRIES E FILMES-percentage":0.09843903810997047,"EDUCAÇÃO-occurances":6,"EDUCAÇÃO-percentage":0.08437631837997468,"POP/ARTE-occurances":4,"POP/ARTE-percentage":0.05625087891998312,"ECONOMIA-occurances":3,"ECONOMIA-percentage":0.04218815918998734,"TWITTER-occurances":3,"TWITTER-percentage":0.04218815918998734,"TV E CELEBRIDADES-occurances":2,"TV E CELEBRIDADES-percentage":0.02812543945999156,"VIAGENS-occurances":2,"VIAGENS-percentage":0.02812543945999156,"POLÍTICA-occurances":1,"POLÍTICA-percentage":0.01406271972999578,"ALIMENTAÇÃO E SAÚDE-occurances":0,"ALIMENTAÇÃO E SAÚDE-percentage":0,"FITNESS-occurances":0,"FITNESS-percentage":0,"HUMOR-occurances":0,"HUMOR-percentage":0,"INTERNACIONAL-occurances":0,"INTERNACIONAL-percentage":0,"JOGOS-occurances":0,"JOGOS-percentage":0,"NATUREZA-occurances":0,"NATUREZA-percentage":0}