{"totalHistoryAmount":1487,"TECNOLOGIA-occurances":584,"TECNOLOGIA-percentage":39.273705447209146,"NOTÍCIAS-occurances":254,"NOTÍCIAS-percentage":17.081371889710827,"ESPORTE-occurances":82,"ESPORTE-percentage":5.514458641560188,"FACEBOOK-occurances":64,"FACEBOOK-percentage":4.303967720242098,"POLÍTICA-occurances":20,"POLÍTICA-percentage":1.3449899125756557,"YOUTUBE-occurances":18,"YOUTUBE-percentage":1.21049092131809,"EDUCAÇÃO-occurances":16,"EDUCAÇÃO-percentage":1.0759919300605245,"MODA-occurances":16,"MODA-percentage":1.0759919300605245,"POP/ARTE-occurances":16,"POP/ARTE-percentage":1.0759919300605245,"JOGOS-occurances":14,"JOGOS-percentage":0.9414929388029589,"SÉRIES E FILMES-occurances":12,"SÉRIES E FILMES-percentage":0.8069939475453934,"TWITTER-occurances":11,"TWITTER-percentage":0.7397444519166106,"LINKEDIN-occurances":8,"LINKEDIN-percentage":0.5379959650302623,"VIAGENS-occurances":5,"VIAGENS-percentage":0.3362474781439139,"DECORAÇÃO-occurances":4,"DECORAÇÃO-percentage":0.26899798251513113,"TV E CELEBRIDADES-occurances":4,"TV E CELEBRIDADES-percentage":0.26899798251513113,"ESOTERISMO-occurances":3,"ESOTERISMO-percentage":0.20174848688634836,"INSTAGRAM-occurances":3,"INSTAGRAM-percentage":0.20174848688634836,"CIÊNCIA-occurances":2,"CIÊNCIA-percentage":0.13449899125756556,"SEXO-occurances":2,"SEXO-percentage":0.13449899125756556,"ALIMENTAÇÃO E SAÚDE-occurances":1,"ALIMENTAÇÃO E SAÚDE-percentage":0.06724949562878278,"CARROS-occurances":1,"CARROS-percentage":0.06724949562878278,"ECONOMIA-occurances":0,"ECONOMIA-percentage":0,"FITNESS-occurances":0,"FITNESS-percentage":0,"HUMOR-occurances":0,"HUMOR-percentage":0,"INTERNACIONAL-occurances":0,"INTERNACIONAL-percentage":0,"NATUREZA-occurances":0,"NATUREZA-percentage":0}